LICENSE
MANIFEST.in
README.md
requirements.txt
setup.py
xplenty3/__init__.py
xplenty3/exceptions.py
xplenty3/xplenty_api.py
xplenty3.egg-info/PKG-INFO
xplenty3.egg-info/SOURCES.txt
xplenty3.egg-info/dependency_links.txt
xplenty3.egg-info/requires.txt
xplenty3.egg-info/top_level.txt