Metadata-Version: 1.0
Name: xplenty3
Version: 0.1.0
Summary: Xplenty API Python SDK
Home-page: https://github.com/apartmentlist/xplenty3.py
Author: Xplenty
Author-email: opensource@xplenty.com
License: MIT
Platform: UNKNOWN
